probaforms/__init__.py
probaforms/metrics/__init__.py
probaforms/metrics/div1d.py
probaforms/metrics/fd.py
probaforms/metrics/ks1d.py
probaforms/metrics/mmd.py
probaforms/models/__init__.py
probaforms/models/cvae.py
probaforms/models/interfaces.py
probaforms/models/nflow.py
probaforms/models/realnvp.py
probaforms/models/wgan.py
probaforms-0.2.0.dist-info/LICENSE
probaforms-0.2.0.dist-info/METADATA
probaforms-0.2.0.dist-info/WHEEL
probaforms-0.2.0.dist-info/RECORD
