Metadata-Version: 2.1
Name: probaforms
Version: 0.2.0
Summary: Synthetic data generation for tables.
Home-page: https://github.com/HSE-LAMBDA/probaforms
License: MIT
Keywords: synthetic data,augmentation,generative models,normalizing flows,VAE,GAN
Author: Mikhail Hushchyn
Author-email: hushchyn.mikhail@gmail.com
Requires-Python: >=3.8,<4.0
Classifier: License :: OSI Approved :: MIT License
Classifier: Programming Language :: Python :: 3
Classifier: Programming Language :: Python :: 3.8
Classifier: Programming Language :: Python :: 3.9
Classifier: Programming Language :: Python :: 3.10
Classifier: Programming Language :: Python :: 3.11
Requires-Dist: matplotlib (>=3.5.1,<4.0.0)
Requires-Dist: numpy (>=1.22.1,<2.0.0)
Requires-Dist: pandas (>=1.4.2,<2.0.0)
Requires-Dist: scikit-learn (>=1.0.2,<2.0.0)
Requires-Dist: torch (>=1.11.0,<2.0.0)
Requires-Dist: tqdm (>=4.64.0,<5.0.0)
Project-URL: Documentation, https://hse-lambda.github.io/probaforms/
Project-URL: Repository, https://github.com/HSE-LAMBDA/probaforms
